{
	"class" : {
		 },
	"instance" : {
		"complexArraysArray" : "mu 5/1/2011 23:45",
		"complexCollectionSizes" : "mu 5/1/2011 23:44",
		"complexMapsArray" : "mu 5/1/2011 23:56",
		"createArraySized:" : "mu 6/23/2011 12:10",
		"createComplexArraySized:" : "mu 6/23/2011 12:11",
		"createComplexMapSized:" : "mu 6/23/2011 12:11",
		"createRawBytesSized:" : "mu 6/23/2011 12:12",
		"createSimpleArraySized:" : "mu 6/23/2011 12:12",
		"createSimpleMapSized:" : "mu 5/1/2011 23:53",
		"floatsArray" : "mu 5/1/2011 22:36",
		"integersArray" : "mu 5/1/2011 21:20",
		"mapSizes" : "mu 5/1/2011 22:49",
		"rawBytesArray" : "mu 5/1/2011 22:50",
		"rawBytesSizes" : "mu 5/1/2011 22:50",
		"simpleArraysArray" : "mu 5/1/2011 23:45",
		"simpleCollectionSizes" : "mu 5/1/2011 23:45",
		"simpleMapsArray" : "mu 5/1/2011 23:50",
		"testPackUnpackArray" : "mu 6/23/2011 12:43",
		"testPackUnpackComplexArray" : "mu 6/23/2011 12:43",
		"testPackUnpackComplexMap" : "mu 6/23/2011 12:43",
		"testPackUnpackFalse" : "mu 5/1/2011 21:39",
		"testPackUnpackFloatingPoint" : "mu 5/1/2011 21:43",
		"testPackUnpackInteger" : "mu 5/1/2011 21:33",
		"testPackUnpackMap" : "mu 6/23/2011 12:44",
		"testPackUnpackNil" : "mu 5/1/2011 21:38",
		"testPackUnpackRawBytes" : "mu 6/23/2011 12:44",
		"testPackUnpackTrue" : "mu 5/1/2011 21:39" } }
