{
	"class" : {
		"array16" : "mu 6/23/2011 12:00",
		"array32" : "mu 6/23/2011 12:00",
		"bin16" : "mu 8/11/2013 23:51",
		"bin32" : "mu 8/11/2013 23:52",
		"bin8" : "mu 8/11/2013 23:51",
		"double" : "mu 6/23/2011 12:01",
		"false" : "mu 6/23/2011 12:01",
		"fixext1" : "mu 8/11/2013 23:54",
		"fixext16" : "mu 8/11/2013 23:54",
		"fixext2" : "mu 8/11/2013 23:54",
		"fixext4" : "mu 8/11/2013 23:54",
		"fixext8" : "mu 8/11/2013 23:54",
		"float" : "mu 6/23/2011 12:01",
		"int16" : "mu 6/23/2011 12:01",
		"int32" : "mu 6/23/2011 12:02",
		"int64" : "mu 6/23/2011 12:02",
		"int8" : "mu 6/23/2011 12:02",
		"map16" : "mu 6/23/2011 12:02",
		"map32" : "mu 6/23/2011 12:02",
		"nil" : "mu 6/23/2011 12:02",
		"str16" : "mu 8/11/2013 23:46",
		"str32" : "mu 8/11/2013 23:47",
		"str8" : "mu 8/11/2013 23:48",
		"true" : "mu 6/23/2011 12:02",
		"uint16" : "mu 6/23/2011 12:02",
		"uint32" : "mu 6/23/2011 12:02",
		"uint64" : "mu 6/23/2011 12:03",
		"uint8" : "mu 6/23/2011 12:03" },
	"instance" : {
		 } }
